__init__.py
extensible_calendar/__init__.py
extensible_calendar/main.py
extensible_calendar/UI/__init__.py
extensible_calendar/UI/calendar_ui.py
extensible_calendar/base_calendar/__init__.py
extensible_calendar/base_calendar/base_calendar.py
extensible_calendar/base_calendar/constants.py
extensible_calendar/base_calendar/solar_terms.py
extensible_calendar/base_calendar/utils.py
test/__init__.py
ExtensibleCalendar-0.0.2.dist-info/LICENSE
ExtensibleCalendar-0.0.2.dist-info/METADATA
ExtensibleCalendar-0.0.2.dist-info/WHEEL
ExtensibleCalendar-0.0.2.dist-info/top_level.txt
ExtensibleCalendar-0.0.2.dist-info/RECORD
