Metadata-Version: 2.1
Name: ExtensibleCalendar
Version: 0.0.2
Summary: 可拓展万年历
Author-email: MasterCoisin <17350199092@163.com>
Project-URL: Homepage, https://github.com/MasterCoisin/ExtensibleCalendar
Project-URL: Bug Tracker, https://github.com/MasterCoisin/ExtensibleCalendar/issues
Classifier: Programming Language :: Python :: 3
Classifier: License :: OSI Approved :: MIT License
Requires-Python: >=3.6
License-File: LICENSE
